tttplots/__init__.py
tttplots/__main__.py
tttplots/tttplots.py
tttplots/version.py
tttplots-0.1.1.dist-info/LICENSE
tttplots-0.1.1.dist-info/METADATA
tttplots-0.1.1.dist-info/WHEEL
tttplots-0.1.1.dist-info/entry_points.txt
tttplots-0.1.1.dist-info/top_level.txt
tttplots-0.1.1.dist-info/RECORD
